django_contrib_validator-1.0.3.dist-info/DESCRIPTION.rst
django_contrib_validator-1.0.3.dist-info/METADATA
django_contrib_validator-1.0.3.dist-info/RECORD
django_contrib_validator-1.0.3.dist-info/WHEEL
django_contrib_validator-1.0.3.dist-info/metadata.json
django_contrib_validator-1.0.3.dist-info/top_level.txt
validator/__init__.py
validator/tests.py
validator/validators.py
