Metadata-Version: 2.0
Name: django-contrib-validator
Version: 1.0.3
Summary: a python data validator
Home-page: https://github.com/universalyouth/validator
Author: younger shen
Author-email: younger.x.shen@gmail.com
License: MIT
Keywords: a python data validator
Platform: UNKNOWN
Classifier: Development Status :: 3 - Alpha
Classifier: Intended Audience :: Developers
Classifier: License :: OSI Approved :: MIT License
Classifier: Programming Language :: Python :: 3.6
